aap_utils/__init__.py
aap_utils/cli.py
aap_utils/register.py
aap_utils-0.2.20.dist-info/METADATA
aap_utils-0.2.20.dist-info/WHEEL
aap_utils-0.2.20.dist-info/entry_points.txt
aap_utils-0.2.20.dist-info/top_level.txt
aap_utils-0.2.20.dist-info/RECORD
