Metadata-Version: 2.1
Name: aap_utils
Version: 0.2.20
Summary: A Python library for registering an IP address for AAP
Author: Minh Dang
Author-email: danghoangminh86@gmail.com
Classifier: Programming Language :: Python :: 3
Classifier: License :: OSI Approved :: MIT License
Classifier: Operating System :: OS Independent
Requires-Dist: requests
Requires-Dist: hydra-core
